arcbeam_connector/__init__.py
arcbeam_connector/langchain/__init__.py
arcbeam_connector/langchain/connector.py
arcbeam_connector-0.0.2.dist-info/METADATA
arcbeam_connector-0.0.2.dist-info/WHEEL
arcbeam_connector-0.0.2.dist-info/RECORD
