Metadata-Version: 2.4
Name: arcbeam-connector
Version: 0.0.2
Summary: Arcbeam connector for AI frameworks.
Author-email: Arcbeam Eng <arcbeameng@gmail.com>
Requires-Python: >=3.9
Requires-Dist: opentelemetry-exporter-otlp>=1.39.1
